{
  "id": "session_006",
  "date": "2024/03/17",
  "coordinates": [
    42.98,
    -81.265
  ],
  "readings": [
    {
      "time": "22:00:00",
      "F1": 3,
      "F2": 3,
      "F3": 4,
      "F4": 4,
      "F5": 5,
      "F6": 4,
      "F7": 3,
      "F8": 2,
      "NIR": 1,
      "Clear": 25
    },
    {
      "time": "22:00:02",
      "F1": 1,
      "F2": 2,
      "F3": 3,
      "F4": 4,
      "F5": 3,
      "F6": 2,
      "F7": 2,
      "F8": 1,
      "NIR": 1,
      "Clear": 17
    },
    {
      "time": "22:00:04",
      "F1": 3,
      "F2": 5,
      "F3": 5,
      "F4": 6,
      "F5": 5,
      "F6": 4,
      "F7": 4,
      "F8": 3,
      "NIR": 2,
      "Clear": 31
    },
    {
      "time": "22:00:06",
      "F1": 2,
      "F2": 3,
      "F3": 3,
      "F4": 5,
      "F5": 4,
      "F6": 3,
      "F7": 3,
      "F8": 2,
      "NIR": 1,
      "Clear": 23
    },
    {
      "time": "22:00:08",
      "F1": 3,
      "F2": 4,
      "F3": 4,
      "F4": 6,
      "F5": 5,
      "F6": 4,
      "F7": 4,
      "F8": 2,
      "NIR": 2,
      "Clear": 31
    },
    {
      "time": "22:00:10",
      "F1": 3,
      "F2": 4,
      "F3": 5,
      "F4": 6,
      "F5": 6,
      "F6": 5,
      "F7": 4,
      "F8": 2,
      "NIR": 2,
      "Clear": 31
    },
    {
      "time": "22:00:12",
      "F1": 3,
      "F2": 3,
      "F3": 5,
      "F4": 6,
      "F5": 5,
      "F6": 4,
      "F7": 4,
      "F8": 3,
      "NIR": 2,
      "Clear": 29
    },
    {
      "time": "22:00:14",
      "F1": 4,
      "F2": 5,
      "F3": 6,
      "F4": 7,
      "F5": 7,
      "F6": 6,
      "F7": 5,
      "F8": 3,
      "NIR": 2,
      "Clear": 36
    },
    {
      "time": "22:00:16",
      "F1": 5,
      "F2": 6,
      "F3": 8,
      "F4": 10,
      "F5": 9,
      "F6": 7,
      "F7": 5,
      "F8": 4,
      "NIR": 3,
      "Clear": 44
    },
    {
      "time": "22:00:18",
      "F1": 6,
      "F2": 7,
      "F3": 7,
      "F4": 10,
      "F5": 10,
      "F6": 8,
      "F7": 7,
      "F8": 4,
      "NIR": 4,
      "Clear": 48
    },
    {
      "time": "22:00:20",
      "F1": 5,
      "F2": 6,
      "F3": 6,
      "F4": 8,
      "F5": 7,
      "F6": 6,
      "F7": 5,
      "F8": 3,
      "NIR": 3,
      "Clear": 38
    },
    {
      "time": "22:00:22",
      "F1": 6,
      "F2": 7,
      "F3": 8,
      "F4": 10,
      "F5": 8,
      "F6": 8,
      "F7": 7,
      "F8": 5,
      "NIR": 4,
      "Clear": 49
    },
    {
      "time": "22:00:24",
      "F1": 5,
      "F2": 6,
      "F3": 8,
      "F4": 9,
      "F5": 9,
      "F6": 7,
      "F7": 6,
      "F8": 4,
      "NIR": 3,
      "Clear": 47
    },
    {
      "time": "22:00:26",
      "F1": 4,
      "F2": 6,
      "F3": 8,
      "F4": 8,
      "F5": 9,
      "F6": 7,
      "F7": 5,
      "F8": 4,
      "NIR": 3,
      "Clear": 45
    },
    {
      "time": "22:00:28",
      "F1": 6,
      "F2": 9,
      "F3": 9,
      "F4": 11,
      "F5": 11,
      "F6": 10,
      "F7": 7,
      "F8": 6,
      "NIR": 4,
      "Clear": 57
    },
    {
      "time": "22:00:30",
      "F1": 7,
      "F2": 9,
      "F3": 10,
      "F4": 12,
      "F5": 12,
      "F6": 9,
      "F7": 7,
      "F8": 6,
      "NIR": 5,
      "Clear": 60
    },
    {
      "time": "22:00:32",
      "F1": 7,
      "F2": 9,
      "F3": 10,
      "F4": 11,
      "F5": 11,
      "F6": 9,
      "F7": 7,
      "F8": 6,
      "NIR": 5,
      "Clear": 58
    },
    {
      "time": "22:00:34",
      "F1": 5,
      "F2": 7,
      "F3": 9,
      "F4": 10,
      "F5": 9,
      "F6": 9,
      "F7": 7,
      "F8": 4,
      "NIR": 4,
      "Clear": 49
    },
    {
      "time": "22:00:36",
      "F1": 7,
      "F2": 7,
      "F3": 9,
      "F4": 12,
      "F5": 11,
      "F6": 9,
      "F7": 8,
      "F8": 5,
      "NIR": 4,
      "Clear": 58
    },
    {
      "time": "22:00:38",
      "F1": 7,
      "F2": 8,
      "F3": 10,
      "F4": 11,
      "F5": 10,
      "F6": 8,
      "F7": 7,
      "F8": 6,
      "NIR": 4,
      "Clear": 55
    },
    {
      "time": "22:00:40",
      "F1": 8,
      "F2": 9,
      "F3": 11,
      "F4": 12,
      "F5": 13,
      "F6": 11,
      "F7": 7,
      "F8": 7,
      "NIR": 5,
      "Clear": 64
    },
    {
      "time": "22:00:42",
      "F1": 6,
      "F2": 9,
      "F3": 12,
      "F4": 13,
      "F5": 14,
      "F6": 11,
      "F7": 8,
      "F8": 6,
      "NIR": 5,
      "Clear": 65
    },
    {
      "time": "22:00:44",
      "F1": 7,
      "F2": 9,
      "F3": 11,
      "F4": 13,
      "F5": 11,
      "F6": 10,
      "F7": 8,
      "F8": 6,
      "NIR": 4,
      "Clear": 61
    },
    {
      "time": "22:00:46",
      "F1": 8,
      "F2": 9,
      "F3": 11,
      "F4": 13,
      "F5": 15,
      "F6": 12,
      "F7": 10,
      "F8": 6,
      "NIR": 5,
      "Clear": 69
    },
    {
      "time": "22:00:48",
      "F1": 8,
      "F2": 10,
      "F3": 14,
      "F4": 17,
      "F5": 15,
      "F6": 13,
      "F7": 10,
      "F8": 7,
      "NIR": 6,
      "Clear": 74
    },
    {
      "time": "22:00:50",
      "F1": 9,
      "F2": 12,
      "F3": 12,
      "F4": 15,
      "F5": 14,
      "F6": 11,
      "F7": 10,
      "F8": 7,
      "NIR": 5,
      "Clear": 73
    },
    {
      "time": "22:00:52",
      "F1": 8,
      "F2": 11,
      "F3": 14,
      "F4": 18,
      "F5": 15,
      "F6": 12,
      "F7": 11,
      "F8": 8,
      "NIR": 6,
      "Clear": 75
    },
    {
      "time": "22:00:54",
      "F1": 7,
      "F2": 9,
      "F3": 11,
      "F4": 15,
      "F5": 14,
      "F6": 10,
      "F7": 9,
      "F8": 6,
      "NIR": 4,
      "Clear": 67
    },
    {
      "time": "22:00:56",
      "F1": 9,
      "F2": 10,
      "F3": 13,
      "F4": 14,
      "F5": 13,
      "F6": 11,
      "F7": 10,
      "F8": 7,
      "NIR": 6,
      "Clear": 71
    },
    {
      "time": "22:00:58",
      "F1": 10,
      "F2": 10,
      "F3": 14,
      "F4": 16,
      "F5": 16,
      "F6": 12,
      "F7": 10,
      "F8": 6,
      "NIR": 6,
      "Clear": 76
    },
    {
      "time": "22:01:00",
      "F1": 7,
      "F2": 10,
      "F3": 12,
      "F4": 16,
      "F5": 13,
      "F6": 11,
      "F7": 10,
      "F8": 7,
      "NIR": 5,
      "Clear": 70
    },
    {
      "time": "22:01:02",
      "F1": 8,
      "F2": 12,
      "F3": 12,
      "F4": 16,
      "F5": 16,
      "F6": 12,
      "F7": 11,
      "F8": 7,
      "NIR": 6,
      "Clear": 79
    },
    {
      "time": "22:01:04",
      "F1": 8,
      "F2": 11,
      "F3": 12,
      "F4": 17,
      "F5": 13,
      "F6": 10,
      "F7": 9,
      "F8": 6,
      "NIR": 5,
      "Clear": 72
    },
    {
      "time": "22:01:06",
      "F1": 9,
      "F2": 10,
      "F3": 14,
      "F4": 17,
      "F5": 14,
      "F6": 13,
      "F7": 10,
      "F8": 6,
      "NIR": 5,
      "Clear": 76
    },
    {
      "time": "22:01:08",
      "F1": 9,
      "F2": 13,
      "F3": 14,
      "F4": 17,
      "F5": 17,
      "F6": 14,
      "F7": 11,
      "F8": 8,
      "NIR": 7,
      "Clear": 82
    },
    {
      "time": "22:01:10",
      "F1": 10,
      "F2": 11,
      "F3": 12,
      "F4": 19,
      "F5": 17,
      "F6": 12,
      "F7": 10,
      "F8": 8,
      "NIR": 5,
      "Clear": 78
    },
    {
      "time": "22:01:12",
      "F1": 10,
      "F2": 11,
      "F3": 14,
      "F4": 19,
      "F5": 15,
      "F6": 15,
      "F7": 11,
      "F8": 8,
      "NIR": 6,
      "Clear": 85
    },
    {
      "time": "22:01:14",
      "F1": 11,
      "F2": 13,
      "F3": 14,
      "F4": 20,
      "F5": 17,
      "F6": 14,
      "F7": 12,
      "F8": 8,
      "NIR": 6,
      "Clear": 90
    },
    {
      "time": "22:01:16",
      "F1": 10,
      "F2": 12,
      "F3": 16,
      "F4": 19,
      "F5": 16,
      "F6": 14,
      "F7": 10,
      "F8": 9,
      "NIR": 6,
      "Clear": 86
    },
    {
      "time": "22:01:18",
      "F1": 9,
      "F2": 11,
      "F3": 14,
      "F4": 17,
      "F5": 16,
      "F6": 13,
      "F7": 12,
      "F8": 8,
      "NIR": 7,
      "Clear": 87
    },
    {
      "time": "22:01:20",
      "F1": 8,
      "F2": 11,
      "F3": 13,
      "F4": 19,
      "F5": 15,
      "F6": 11,
      "F7": 11,
      "F8": 8,
      "NIR": 6,
      "Clear": 80
    },
    {
      "time": "22:01:22",
      "F1": 9,
      "F2": 11,
      "F3": 15,
      "F4": 20,
      "F5": 15,
      "F6": 13,
      "F7": 11,
      "F8": 9,
      "NIR": 6,
      "Clear": 87
    },
    {
      "time": "22:01:24",
      "F1": 9,
      "F2": 11,
      "F3": 13,
      "F4": 17,
      "F5": 18,
      "F6": 13,
      "F7": 12,
      "F8": 7,
      "NIR": 7,
      "Clear": 84
    },
    {
      "time": "22:01:26",
      "F1": 10,
      "F2": 12,
      "F3": 12,
      "F4": 16,
      "F5": 15,
      "F6": 13,
      "F7": 11,
      "F8": 6,
      "NIR": 6,
      "Clear": 77
    },
    {
      "time": "22:01:28",
      "F1": 9,
      "F2": 13,
      "F3": 13,
      "F4": 16,
      "F5": 17,
      "F6": 14,
      "F7": 11,
      "F8": 8,
      "NIR": 5,
      "Clear": 79
    },
    {
      "time": "22:01:30",
      "F1": 9,
      "F2": 14,
      "F3": 14,
      "F4": 18,
      "F5": 17,
      "F6": 16,
      "F7": 12,
      "F8": 8,
      "NIR": 6,
      "Clear": 88
    },
    {
      "time": "22:01:32",
      "F1": 8,
      "F2": 12,
      "F3": 15,
      "F4": 20,
      "F5": 14,
      "F6": 15,
      "F7": 10,
      "F8": 8,
      "NIR": 5,
      "Clear": 82
    },
    {
      "time": "22:01:34",
      "F1": 9,
      "F2": 12,
      "F3": 15,
      "F4": 18,
      "F5": 16,
      "F6": 13,
      "F7": 12,
      "F8": 8,
      "NIR": 6,
      "Clear": 80
    },
    {
      "time": "22:01:36",
      "F1": 10,
      "F2": 11,
      "F3": 15,
      "F4": 17,
      "F5": 16,
      "F6": 14,
      "F7": 11,
      "F8": 9,
      "NIR": 6,
      "Clear": 84
    },
    {
      "time": "22:01:38",
      "F1": 9,
      "F2": 14,
      "F3": 15,
      "F4": 21,
      "F5": 19,
      "F6": 16,
      "F7": 11,
      "F8": 9,
      "NIR": 6,
      "Clear": 91
    },
    {
      "time": "22:01:40",
      "F1": 9,
      "F2": 12,
      "F3": 16,
      "F4": 19,
      "F5": 17,
      "F6": 15,
      "F7": 13,
      "F8": 8,
      "NIR": 7,
      "Clear": 91
    },
    {
      "time": "22:01:42",
      "F1": 8,
      "F2": 12,
      "F3": 15,
      "F4": 16,
      "F5": 16,
      "F6": 14,
      "F7": 10,
      "F8": 7,
      "NIR": 6,
      "Clear": 82
    },
    {
      "time": "22:01:44",
      "F1": 9,
      "F2": 12,
      "F3": 14,
      "F4": 19,
      "F5": 18,
      "F6": 13,
      "F7": 10,
      "F8": 7,
      "NIR": 6,
      "Clear": 84
    },
    {
      "time": "22:01:46",
      "F1": 10,
      "F2": 12,
      "F3": 15,
      "F4": 19,
      "F5": 15,
      "F6": 14,
      "F7": 10,
      "F8": 7,
      "NIR": 7,
      "Clear": 83
    },
    {
      "time": "22:01:48",
      "F1": 10,
      "F2": 13,
      "F3": 16,
      "F4": 17,
      "F5": 16,
      "F6": 13,
      "F7": 12,
      "F8": 9,
      "NIR": 6,
      "Clear": 88
    },
    {
      "time": "22:01:50",
      "F1": 9,
      "F2": 13,
      "F3": 14,
      "F4": 17,
      "F5": 17,
      "F6": 14,
      "F7": 10,
      "F8": 8,
      "NIR": 7,
      "Clear": 82
    },
    {
      "time": "22:01:52",
      "F1": 10,
      "F2": 13,
      "F3": 15,
      "F4": 19,
      "F5": 18,
      "F6": 13,
      "F7": 11,
      "F8": 8,
      "NIR": 6,
      "Clear": 85
    },
    {
      "time": "22:01:54",
      "F1": 11,
      "F2": 12,
      "F3": 15,
      "F4": 20,
      "F5": 15,
      "F6": 14,
      "F7": 12,
      "F8": 7,
      "NIR": 6,
      "Clear": 85
    },
    {
      "time": "22:01:56",
      "F1": 10,
      "F2": 11,
      "F3": 13,
      "F4": 19,
      "F5": 17,
      "F6": 14,
      "F7": 10,
      "F8": 8,
      "NIR": 7,
      "Clear": 79
    },
    {
      "time": "22:01:58",
      "F1": 8,
      "F2": 11,
      "F3": 14,
      "F4": 17,
      "F5": 14,
      "F6": 13,
      "F7": 11,
      "F8": 7,
      "NIR": 6,
      "Clear": 75
    },
    {
      "time": "22:02:00",
      "F1": 8,
      "F2": 11,
      "F3": 13,
      "F4": 16,
      "F5": 16,
      "F6": 14,
      "F7": 11,
      "F8": 8,
      "NIR": 6,
      "Clear": 77
    },
    {
      "time": "22:02:02",
      "F1": 8,
      "F2": 10,
      "F3": 13,
      "F4": 16,
      "F5": 15,
      "F6": 13,
      "F7": 10,
      "F8": 8,
      "NIR": 6,
      "Clear": 77
    },
    {
      "time": "22:02:04",
      "F1": 8,
      "F2": 11,
      "F3": 12,
      "F4": 13,
      "F5": 12,
      "F6": 12,
      "F7": 8,
      "F8": 7,
      "NIR": 5,
      "Clear": 69
    },
    {
      "time": "22:02:06",
      "F1": 7,
      "F2": 11,
      "F3": 12,
      "F4": 14,
      "F5": 14,
      "F6": 10,
      "F7": 10,
      "F8": 6,
      "NIR": 5,
      "Clear": 68
    },
    {
      "time": "22:02:08",
      "F1": 9,
      "F2": 11,
      "F3": 13,
      "F4": 15,
      "F5": 15,
      "F6": 13,
      "F7": 9,
      "F8": 7,
      "NIR": 6,
      "Clear": 74
    },
    {
      "time": "22:02:10",
      "F1": 8,
      "F2": 11,
      "F3": 11,
      "F4": 14,
      "F5": 11,
      "F6": 10,
      "F7": 9,
      "F8": 7,
      "NIR": 5,
      "Clear": 66
    },
    {
      "time": "22:02:12",
      "F1": 9,
      "F2": 11,
      "F3": 13,
      "F4": 16,
      "F5": 14,
      "F6": 12,
      "F7": 10,
      "F8": 8,
      "NIR": 5,
      "Clear": 72
    },
    {
      "time": "22:02:14",
      "F1": 7,
      "F2": 8,
      "F3": 9,
      "F4": 13,
      "F5": 11,
      "F6": 10,
      "F7": 8,
      "F8": 5,
      "NIR": 4,
      "Clear": 60
    },
    {
      "time": "22:02:16",
      "F1": 6,
      "F2": 9,
      "F3": 9,
      "F4": 11,
      "F5": 11,
      "F6": 8,
      "F7": 9,
      "F8": 6,
      "NIR": 4,
      "Clear": 59
    },
    {
      "time": "22:02:18",
      "F1": 7,
      "F2": 8,
      "F3": 11,
      "F4": 13,
      "F5": 11,
      "F6": 9,
      "F7": 7,
      "F8": 6,
      "NIR": 4,
      "Clear": 62
    },
    {
      "time": "22:02:20",
      "F1": 6,
      "F2": 8,
      "F3": 10,
      "F4": 12,
      "F5": 11,
      "F6": 9,
      "F7": 8,
      "F8": 6,
      "NIR": 5,
      "Clear": 60
    },
    {
      "time": "22:02:22",
      "F1": 8,
      "F2": 8,
      "F3": 11,
      "F4": 13,
      "F5": 13,
      "F6": 11,
      "F7": 9,
      "F8": 6,
      "NIR": 5,
      "Clear": 63
    },
    {
      "time": "22:02:24",
      "F1": 6,
      "F2": 8,
      "F3": 9,
      "F4": 11,
      "F5": 10,
      "F6": 9,
      "F7": 7,
      "F8": 5,
      "NIR": 4,
      "Clear": 53
    },
    {
      "time": "22:02:26",
      "F1": 5,
      "F2": 8,
      "F3": 8,
      "F4": 11,
      "F5": 11,
      "F6": 8,
      "F7": 8,
      "F8": 5,
      "NIR": 3,
      "Clear": 53
    },
    {
      "time": "22:02:28",
      "F1": 5,
      "F2": 7,
      "F3": 8,
      "F4": 9,
      "F5": 8,
      "F6": 7,
      "F7": 6,
      "F8": 5,
      "NIR": 3,
      "Clear": 45
    },
    {
      "time": "22:02:30",
      "F1": 7,
      "F2": 8,
      "F3": 8,
      "F4": 11,
      "F5": 10,
      "F6": 8,
      "F7": 6,
      "F8": 5,
      "NIR": 4,
      "Clear": 53
    },
    {
      "time": "22:02:32",
      "F1": 5,
      "F2": 6,
      "F3": 8,
      "F4": 11,
      "F5": 9,
      "F6": 7,
      "F7": 7,
      "F8": 4,
      "NIR": 4,
      "Clear": 49
    },
    {
      "time": "22:02:34",
      "F1": 6,
      "F2": 7,
      "F3": 9,
      "F4": 9,
      "F5": 10,
      "F6": 7,
      "F7": 7,
      "F8": 4,
      "NIR": 3,
      "Clear": 48
    },
    {
      "time": "22:02:36",
      "F1": 5,
      "F2": 7,
      "F3": 8,
      "F4": 10,
      "F5": 9,
      "F6": 7,
      "F7": 6,
      "F8": 5,
      "NIR": 3,
      "Clear": 48
    },
    {
      "time": "22:02:38",
      "F1": 5,
      "F2": 7,
      "F3": 9,
      "F4": 11,
      "F5": 10,
      "F6": 8,
      "F7": 7,
      "F8": 4,
      "NIR": 3,
      "Clear": 49
    },
    {
      "time": "22:02:40",
      "F1": 3,
      "F2": 5,
      "F3": 6,
      "F4": 8,
      "F5": 6,
      "F6": 6,
      "F7": 5,
      "F8": 3,
      "NIR": 2,
      "Clear": 34
    },
    {
      "time": "22:02:42",
      "F1": 4,
      "F2": 5,
      "F3": 6,
      "F4": 9,
      "F5": 7,
      "F6": 6,
      "F7": 6,
      "F8": 4,
      "NIR": 3,
      "Clear": 40
    },
    {
      "time": "22:02:44",
      "F1": 5,
      "F2": 6,
      "F3": 7,
      "F4": 8,
      "F5": 7,
      "F6": 6,
      "F7": 6,
      "F8": 4,
      "NIR": 3,
      "Clear": 42
    },
    {
      "time": "22:02:46",
      "F1": 3,
      "F2": 3,
      "F3": 4,
      "F4": 6,
      "F5": 5,
      "F6": 4,
      "F7": 3,
      "F8": 2,
      "NIR": 2,
      "Clear": 27
    },
    {
      "time": "22:02:48",
      "F1": 3,
      "F2": 4,
      "F3": 5,
      "F4": 6,
      "F5": 6,
      "F6": 5,
      "F7": 4,
      "F8": 3,
      "NIR": 2,
      "Clear": 32
    },
    {
      "time": "22:02:50",
      "F1": 2,
      "F2": 3,
      "F3": 4,
      "F4": 4,
      "F5": 4,
      "F6": 3,
      "F7": 2,
      "F8": 2,
      "NIR": 1,
      "Clear": 23
    },
    {
      "time": "22:02:52",
      "F1": 3,
      "F2": 4,
      "F3": 5,
      "F4": 7,
      "F5": 5,
      "F6": 4,
      "F7": 3,
      "F8": 3,
      "NIR": 2,
      "Clear": 32
    },
    {
      "time": "22:02:54",
      "F1": 2,
      "F2": 3,
      "F3": 4,
      "F4": 5,
      "F5": 5,
      "F6": 4,
      "F7": 3,
      "F8": 2,
      "NIR": 1,
      "Clear": 25
    },
    {
      "time": "22:02:56",
      "F1": 2,
      "F2": 2,
      "F3": 2,
      "F4": 3,
      "F5": 3,
      "F6": 2,
      "F7": 2,
      "F8": 1,
      "NIR": 1,
      "Clear": 17
    },
    {
      "time": "22:02:58",
      "F1": 2,
      "F2": 3,
      "F3": 4,
      "F4": 5,
      "F5": 4,
      "F6": 4,
      "F7": 3,
      "F8": 2,
      "NIR": 2,
      "Clear": 24
    }
  ]
}