{
  "id": "session_004",
  "date": "2024/03/16",
  "coordinates": [
    42.968,
    -81.26
  ],
  "readings": [
    {
      "time": "20:30:00",
      "F1": 6,
      "F2": 8,
      "F3": 9,
      "F4": 13,
      "F5": 11,
      "F6": 10,
      "F7": 7,
      "F8": 5,
      "NIR": 4,
      "Clear": 57
    },
    {
      "time": "20:30:02",
      "F1": 6,
      "F2": 7,
      "F3": 8,
      "F4": 12,
      "F5": 10,
      "F6": 8,
      "F7": 7,
      "F8": 5,
      "NIR": 3,
      "Clear": 53
    },
    {
      "time": "20:30:04",
      "F1": 8,
      "F2": 9,
      "F3": 10,
      "F4": 16,
      "F5": 12,
      "F6": 10,
      "F7": 8,
      "F8": 7,
      "NIR": 5,
      "Clear": 66
    },
    {
      "time": "20:30:06",
      "F1": 8,
      "F2": 10,
      "F3": 13,
      "F4": 14,
      "F5": 13,
      "F6": 12,
      "F7": 9,
      "F8": 7,
      "NIR": 5,
      "Clear": 69
    },
    {
      "time": "20:30:08",
      "F1": 7,
      "F2": 9,
      "F3": 12,
      "F4": 14,
      "F5": 13,
      "F6": 10,
      "F7": 9,
      "F8": 7,
      "NIR": 5,
      "Clear": 71
    },
    {
      "time": "20:30:10",
      "F1": 7,
      "F2": 9,
      "F3": 13,
      "F4": 15,
      "F5": 14,
      "F6": 10,
      "F7": 10,
      "F8": 6,
      "NIR": 5,
      "Clear": 69
    },
    {
      "time": "20:30:12",
      "F1": 10,
      "F2": 12,
      "F3": 15,
      "F4": 19,
      "F5": 17,
      "F6": 13,
      "F7": 10,
      "F8": 7,
      "NIR": 6,
      "Clear": 82
    },
    {
      "time": "20:30:14",
      "F1": 9,
      "F2": 11,
      "F3": 12,
      "F4": 16,
      "F5": 14,
      "F6": 13,
      "F7": 10,
      "F8": 6,
      "NIR": 5,
      "Clear": 73
    },
    {
      "time": "20:30:16",
      "F1": 9,
      "F2": 12,
      "F3": 16,
      "F4": 17,
      "F5": 15,
      "F6": 15,
      "F7": 11,
      "F8": 7,
      "NIR": 5,
      "Clear": 82
    },
    {
      "time": "20:30:18",
      "F1": 9,
      "F2": 12,
      "F3": 13,
      "F4": 15,
      "F5": 15,
      "F6": 14,
      "F7": 10,
      "F8": 8,
      "NIR": 6,
      "Clear": 78
    },
    {
      "time": "20:30:20",
      "F1": 9,
      "F2": 12,
      "F3": 14,
      "F4": 16,
      "F5": 16,
      "F6": 12,
      "F7": 10,
      "F8": 7,
      "NIR": 7,
      "Clear": 79
    },
    {
      "time": "20:30:22",
      "F1": 10,
      "F2": 14,
      "F3": 15,
      "F4": 23,
      "F5": 20,
      "F6": 15,
      "F7": 13,
      "F8": 9,
      "NIR": 7,
      "Clear": 96
    },
    {
      "time": "20:30:24",
      "F1": 11,
      "F2": 15,
      "F3": 17,
      "F4": 18,
      "F5": 18,
      "F6": 14,
      "F7": 15,
      "F8": 10,
      "NIR": 8,
      "Clear": 98
    },
    {
      "time": "20:30:26",
      "F1": 9,
      "F2": 15,
      "F3": 18,
      "F4": 18,
      "F5": 18,
      "F6": 14,
      "F7": 13,
      "F8": 9,
      "NIR": 6,
      "Clear": 93
    },
    {
      "time": "20:30:28",
      "F1": 12,
      "F2": 14,
      "F3": 19,
      "F4": 21,
      "F5": 18,
      "F6": 16,
      "F7": 14,
      "F8": 9,
      "NIR": 7,
      "Clear": 99
    },
    {
      "time": "20:30:30",
      "F1": 13,
      "F2": 16,
      "F3": 20,
      "F4": 22,
      "F5": 20,
      "F6": 18,
      "F7": 15,
      "F8": 10,
      "NIR": 8,
      "Clear": 111
    },
    {
      "time": "20:30:32",
      "F1": 12,
      "F2": 13,
      "F3": 19,
      "F4": 23,
      "F5": 17,
      "F6": 15,
      "F7": 14,
      "F8": 9,
      "NIR": 7,
      "Clear": 99
    },
    {
      "time": "20:30:34",
      "F1": 14,
      "F2": 17,
      "F3": 22,
      "F4": 27,
      "F5": 21,
      "F6": 17,
      "F7": 15,
      "F8": 11,
      "NIR": 9,
      "Clear": 116
    },
    {
      "time": "20:30:36",
      "F1": 14,
      "F2": 19,
      "F3": 18,
      "F4": 24,
      "F5": 22,
      "F6": 21,
      "F7": 15,
      "F8": 10,
      "NIR": 9,
      "Clear": 115
    },
    {
      "time": "20:30:38",
      "F1": 12,
      "F2": 15,
      "F3": 22,
      "F4": 24,
      "F5": 24,
      "F6": 19,
      "F7": 14,
      "F8": 12,
      "NIR": 9,
      "Clear": 113
    },
    {
      "time": "20:30:40",
      "F1": 16,
      "F2": 20,
      "F3": 20,
      "F4": 27,
      "F5": 23,
      "F6": 20,
      "F7": 15,
      "F8": 12,
      "NIR": 11,
      "Clear": 125
    },
    {
      "time": "20:30:42",
      "F1": 14,
      "F2": 17,
      "F3": 20,
      "F4": 28,
      "F5": 26,
      "F6": 20,
      "F7": 17,
      "F8": 10,
      "NIR": 8,
      "Clear": 117
    },
    {
      "time": "20:30:44",
      "F1": 16,
      "F2": 19,
      "F3": 24,
      "F4": 25,
      "F5": 26,
      "F6": 22,
      "F7": 19,
      "F8": 12,
      "NIR": 11,
      "Clear": 131
    },
    {
      "time": "20:30:46",
      "F1": 13,
      "F2": 18,
      "F3": 22,
      "F4": 24,
      "F5": 21,
      "F6": 22,
      "F7": 15,
      "F8": 12,
      "NIR": 9,
      "Clear": 119
    },
    {
      "time": "20:30:48",
      "F1": 15,
      "F2": 19,
      "F3": 25,
      "F4": 25,
      "F5": 26,
      "F6": 20,
      "F7": 17,
      "F8": 13,
      "NIR": 9,
      "Clear": 127
    },
    {
      "time": "20:30:50",
      "F1": 16,
      "F2": 17,
      "F3": 22,
      "F4": 31,
      "F5": 28,
      "F6": 19,
      "F7": 16,
      "F8": 12,
      "NIR": 11,
      "Clear": 128
    },
    {
      "time": "20:30:52",
      "F1": 18,
      "F2": 20,
      "F3": 23,
      "F4": 33,
      "F5": 29,
      "F6": 24,
      "F7": 21,
      "F8": 14,
      "NIR": 9,
      "Clear": 140
    },
    {
      "time": "20:30:54",
      "F1": 16,
      "F2": 21,
      "F3": 28,
      "F4": 28,
      "F5": 25,
      "F6": 21,
      "F7": 19,
      "F8": 13,
      "NIR": 11,
      "Clear": 141
    },
    {
      "time": "20:30:56",
      "F1": 15,
      "F2": 21,
      "F3": 24,
      "F4": 31,
      "F5": 31,
      "F6": 26,
      "F7": 17,
      "F8": 13,
      "NIR": 10,
      "Clear": 142
    },
    {
      "time": "20:30:58",
      "F1": 16,
      "F2": 20,
      "F3": 22,
      "F4": 30,
      "F5": 26,
      "F6": 22,
      "F7": 16,
      "F8": 11,
      "NIR": 11,
      "Clear": 133
    },
    {
      "time": "20:31:00",
      "F1": 18,
      "F2": 24,
      "F3": 27,
      "F4": 30,
      "F5": 27,
      "F6": 24,
      "F7": 23,
      "F8": 16,
      "NIR": 13,
      "Clear": 150
    },
    {
      "time": "20:31:02",
      "F1": 16,
      "F2": 21,
      "F3": 24,
      "F4": 35,
      "F5": 33,
      "F6": 25,
      "F7": 21,
      "F8": 13,
      "NIR": 13,
      "Clear": 152
    },
    {
      "time": "20:31:04",
      "F1": 20,
      "F2": 24,
      "F3": 30,
      "F4": 30,
      "F5": 32,
      "F6": 25,
      "F7": 23,
      "F8": 16,
      "NIR": 13,
      "Clear": 154
    },
    {
      "time": "20:31:06",
      "F1": 17,
      "F2": 24,
      "F3": 25,
      "F4": 37,
      "F5": 33,
      "F6": 24,
      "F7": 23,
      "F8": 15,
      "NIR": 11,
      "Clear": 155
    },
    {
      "time": "20:31:08",
      "F1": 17,
      "F2": 20,
      "F3": 26,
      "F4": 33,
      "F5": 34,
      "F6": 29,
      "F7": 20,
      "F8": 16,
      "NIR": 12,
      "Clear": 157
    },
    {
      "time": "20:31:10",
      "F1": 19,
      "F2": 26,
      "F3": 26,
      "F4": 39,
      "F5": 29,
      "F6": 30,
      "F7": 21,
      "F8": 14,
      "NIR": 12,
      "Clear": 162
    },
    {
      "time": "20:31:12",
      "F1": 18,
      "F2": 24,
      "F3": 28,
      "F4": 34,
      "F5": 32,
      "F6": 25,
      "F7": 23,
      "F8": 14,
      "NIR": 14,
      "Clear": 160
    },
    {
      "time": "20:31:14",
      "F1": 20,
      "F2": 25,
      "F3": 29,
      "F4": 33,
      "F5": 28,
      "F6": 28,
      "F7": 21,
      "F8": 15,
      "NIR": 13,
      "Clear": 159
    },
    {
      "time": "20:31:16",
      "F1": 18,
      "F2": 23,
      "F3": 28,
      "F4": 35,
      "F5": 31,
      "F6": 25,
      "F7": 22,
      "F8": 18,
      "NIR": 13,
      "Clear": 163
    },
    {
      "time": "20:31:18",
      "F1": 20,
      "F2": 23,
      "F3": 30,
      "F4": 32,
      "F5": 31,
      "F6": 28,
      "F7": 23,
      "F8": 17,
      "NIR": 13,
      "Clear": 168
    },
    {
      "time": "20:31:20",
      "F1": 18,
      "F2": 24,
      "F3": 31,
      "F4": 38,
      "F5": 29,
      "F6": 24,
      "F7": 22,
      "F8": 16,
      "NIR": 12,
      "Clear": 162
    },
    {
      "time": "20:31:22",
      "F1": 21,
      "F2": 26,
      "F3": 28,
      "F4": 34,
      "F5": 30,
      "F6": 27,
      "F7": 23,
      "F8": 18,
      "NIR": 12,
      "Clear": 170
    },
    {
      "time": "20:31:24",
      "F1": 20,
      "F2": 22,
      "F3": 31,
      "F4": 36,
      "F5": 30,
      "F6": 29,
      "F7": 20,
      "F8": 17,
      "NIR": 14,
      "Clear": 165
    },
    {
      "time": "20:31:26",
      "F1": 19,
      "F2": 22,
      "F3": 32,
      "F4": 35,
      "F5": 28,
      "F6": 25,
      "F7": 24,
      "F8": 16,
      "NIR": 13,
      "Clear": 162
    },
    {
      "time": "20:31:28",
      "F1": 23,
      "F2": 26,
      "F3": 34,
      "F4": 41,
      "F5": 35,
      "F6": 30,
      "F7": 24,
      "F8": 18,
      "NIR": 13,
      "Clear": 172
    },
    {
      "time": "20:31:30",
      "F1": 22,
      "F2": 26,
      "F3": 30,
      "F4": 36,
      "F5": 36,
      "F6": 32,
      "F7": 24,
      "F8": 18,
      "NIR": 13,
      "Clear": 177
    },
    {
      "time": "20:31:32",
      "F1": 18,
      "F2": 23,
      "F3": 28,
      "F4": 36,
      "F5": 30,
      "F6": 26,
      "F7": 24,
      "F8": 17,
      "NIR": 11,
      "Clear": 165
    },
    {
      "time": "20:31:34",
      "F1": 20,
      "F2": 25,
      "F3": 28,
      "F4": 36,
      "F5": 37,
      "F6": 29,
      "F7": 25,
      "F8": 18,
      "NIR": 14,
      "Clear": 171
    },
    {
      "time": "20:31:36",
      "F1": 18,
      "F2": 24,
      "F3": 32,
      "F4": 41,
      "F5": 38,
      "F6": 28,
      "F7": 25,
      "F8": 17,
      "NIR": 14,
      "Clear": 172
    },
    {
      "time": "20:31:38",
      "F1": 19,
      "F2": 25,
      "F3": 27,
      "F4": 35,
      "F5": 35,
      "F6": 28,
      "F7": 21,
      "F8": 16,
      "NIR": 12,
      "Clear": 170
    },
    {
      "time": "20:31:40",
      "F1": 18,
      "F2": 26,
      "F3": 32,
      "F4": 34,
      "F5": 36,
      "F6": 27,
      "F7": 24,
      "F8": 15,
      "NIR": 13,
      "Clear": 178
    },
    {
      "time": "20:31:42",
      "F1": 19,
      "F2": 27,
      "F3": 30,
      "F4": 40,
      "F5": 37,
      "F6": 27,
      "F7": 21,
      "F8": 15,
      "NIR": 13,
      "Clear": 172
    },
    {
      "time": "20:31:44",
      "F1": 21,
      "F2": 28,
      "F3": 35,
      "F4": 42,
      "F5": 39,
      "F6": 34,
      "F7": 24,
      "F8": 16,
      "NIR": 13,
      "Clear": 185
    },
    {
      "time": "20:31:46",
      "F1": 21,
      "F2": 26,
      "F3": 28,
      "F4": 39,
      "F5": 36,
      "F6": 26,
      "F7": 24,
      "F8": 18,
      "NIR": 12,
      "Clear": 172
    },
    {
      "time": "20:31:48",
      "F1": 24,
      "F2": 24,
      "F3": 29,
      "F4": 38,
      "F5": 38,
      "F6": 34,
      "F7": 24,
      "F8": 19,
      "NIR": 13,
      "Clear": 183
    },
    {
      "time": "20:31:50",
      "F1": 22,
      "F2": 24,
      "F3": 34,
      "F4": 43,
      "F5": 37,
      "F6": 28,
      "F7": 28,
      "F8": 19,
      "NIR": 14,
      "Clear": 182
    },
    {
      "time": "20:31:52",
      "F1": 20,
      "F2": 26,
      "F3": 30,
      "F4": 42,
      "F5": 38,
      "F6": 27,
      "F7": 27,
      "F8": 18,
      "NIR": 15,
      "Clear": 178
    },
    {
      "time": "20:31:54",
      "F1": 21,
      "F2": 28,
      "F3": 36,
      "F4": 38,
      "F5": 39,
      "F6": 31,
      "F7": 25,
      "F8": 18,
      "NIR": 15,
      "Clear": 183
    },
    {
      "time": "20:31:56",
      "F1": 22,
      "F2": 28,
      "F3": 28,
      "F4": 42,
      "F5": 33,
      "F6": 29,
      "F7": 25,
      "F8": 17,
      "NIR": 12,
      "Clear": 176
    },
    {
      "time": "20:31:58",
      "F1": 20,
      "F2": 25,
      "F3": 35,
      "F4": 39,
      "F5": 40,
      "F6": 32,
      "F7": 24,
      "F8": 16,
      "NIR": 16,
      "Clear": 185
    },
    {
      "time": "20:32:00",
      "F1": 21,
      "F2": 25,
      "F3": 33,
      "F4": 39,
      "F5": 35,
      "F6": 29,
      "F7": 25,
      "F8": 15,
      "NIR": 12,
      "Clear": 173
    },
    {
      "time": "20:32:02",
      "F1": 20,
      "F2": 27,
      "F3": 32,
      "F4": 40,
      "F5": 35,
      "F6": 32,
      "F7": 24,
      "F8": 19,
      "NIR": 13,
      "Clear": 182
    },
    {
      "time": "20:32:04",
      "F1": 19,
      "F2": 24,
      "F3": 28,
      "F4": 38,
      "F5": 37,
      "F6": 27,
      "F7": 22,
      "F8": 17,
      "NIR": 14,
      "Clear": 175
    },
    {
      "time": "20:32:06",
      "F1": 22,
      "F2": 26,
      "F3": 30,
      "F4": 38,
      "F5": 34,
      "F6": 29,
      "F7": 23,
      "F8": 18,
      "NIR": 14,
      "Clear": 187
    },
    {
      "time": "20:32:08",
      "F1": 22,
      "F2": 29,
      "F3": 30,
      "F4": 44,
      "F5": 37,
      "F6": 34,
      "F7": 26,
      "F8": 18,
      "NIR": 14,
      "Clear": 186
    },
    {
      "time": "20:32:10",
      "F1": 18,
      "F2": 28,
      "F3": 30,
      "F4": 41,
      "F5": 33,
      "F6": 26,
      "F7": 24,
      "F8": 15,
      "NIR": 12,
      "Clear": 173
    },
    {
      "time": "20:32:12",
      "F1": 20,
      "F2": 30,
      "F3": 29,
      "F4": 41,
      "F5": 36,
      "F6": 32,
      "F7": 23,
      "F8": 17,
      "NIR": 14,
      "Clear": 179
    },
    {
      "time": "20:32:14",
      "F1": 22,
      "F2": 29,
      "F3": 30,
      "F4": 39,
      "F5": 36,
      "F6": 31,
      "F7": 27,
      "F8": 16,
      "NIR": 13,
      "Clear": 176
    },
    {
      "time": "20:32:16",
      "F1": 19,
      "F2": 24,
      "F3": 28,
      "F4": 34,
      "F5": 35,
      "F6": 31,
      "F7": 23,
      "F8": 16,
      "NIR": 15,
      "Clear": 179
    },
    {
      "time": "20:32:18",
      "F1": 21,
      "F2": 28,
      "F3": 35,
      "F4": 42,
      "F5": 36,
      "F6": 31,
      "F7": 27,
      "F8": 17,
      "NIR": 14,
      "Clear": 179
    },
    {
      "time": "20:32:20",
      "F1": 23,
      "F2": 28,
      "F3": 28,
      "F4": 35,
      "F5": 33,
      "F6": 31,
      "F7": 25,
      "F8": 16,
      "NIR": 12,
      "Clear": 177
    },
    {
      "time": "20:32:22",
      "F1": 22,
      "F2": 29,
      "F3": 31,
      "F4": 38,
      "F5": 31,
      "F6": 26,
      "F7": 24,
      "F8": 16,
      "NIR": 13,
      "Clear": 177
    },
    {
      "time": "20:32:24",
      "F1": 22,
      "F2": 26,
      "F3": 30,
      "F4": 40,
      "F5": 37,
      "F6": 29,
      "F7": 21,
      "F8": 14,
      "NIR": 14,
      "Clear": 166
    },
    {
      "time": "20:32:26",
      "F1": 21,
      "F2": 28,
      "F3": 28,
      "F4": 38,
      "F5": 35,
      "F6": 29,
      "F7": 21,
      "F8": 16,
      "NIR": 13,
      "Clear": 171
    },
    {
      "time": "20:32:28",
      "F1": 22,
      "F2": 24,
      "F3": 32,
      "F4": 36,
      "F5": 38,
      "F6": 31,
      "F7": 24,
      "F8": 17,
      "NIR": 13,
      "Clear": 173
    },
    {
      "time": "20:32:30",
      "F1": 22,
      "F2": 24,
      "F3": 29,
      "F4": 40,
      "F5": 34,
      "F6": 28,
      "F7": 22,
      "F8": 15,
      "NIR": 12,
      "Clear": 166
    },
    {
      "time": "20:32:32",
      "F1": 21,
      "F2": 27,
      "F3": 28,
      "F4": 38,
      "F5": 37,
      "F6": 28,
      "F7": 25,
      "F8": 15,
      "NIR": 15,
      "Clear": 172
    },
    {
      "time": "20:32:34",
      "F1": 18,
      "F2": 23,
      "F3": 30,
      "F4": 37,
      "F5": 30,
      "F6": 31,
      "F7": 25,
      "F8": 16,
      "NIR": 12,
      "Clear": 168
    },
    {
      "time": "20:32:36",
      "F1": 20,
      "F2": 26,
      "F3": 30,
      "F4": 35,
      "F5": 36,
      "F6": 32,
      "F7": 22,
      "F8": 17,
      "NIR": 13,
      "Clear": 170
    },
    {
      "time": "20:32:38",
      "F1": 20,
      "F2": 27,
      "F3": 33,
      "F4": 35,
      "F5": 36,
      "F6": 28,
      "F7": 26,
      "F8": 17,
      "NIR": 14,
      "Clear": 170
    },
    {
      "time": "20:32:40",
      "F1": 18,
      "F2": 24,
      "F3": 31,
      "F4": 34,
      "F5": 28,
      "F6": 27,
      "F7": 21,
      "F8": 15,
      "NIR": 12,
      "Clear": 158
    },
    {
      "time": "20:32:42",
      "F1": 18,
      "F2": 22,
      "F3": 29,
      "F4": 35,
      "F5": 29,
      "F6": 28,
      "F7": 19,
      "F8": 16,
      "NIR": 13,
      "Clear": 159
    },
    {
      "time": "20:32:44",
      "F1": 19,
      "F2": 25,
      "F3": 31,
      "F4": 39,
      "F5": 32,
      "F6": 24,
      "F7": 22,
      "F8": 16,
      "NIR": 14,
      "Clear": 163
    },
    {
      "time": "20:32:46",
      "F1": 19,
      "F2": 24,
      "F3": 28,
      "F4": 37,
      "F5": 31,
      "F6": 28,
      "F7": 20,
      "F8": 16,
      "NIR": 14,
      "Clear": 162
    },
    {
      "time": "20:32:48",
      "F1": 19,
      "F2": 23,
      "F3": 29,
      "F4": 36,
      "F5": 33,
      "F6": 25,
      "F7": 20,
      "F8": 15,
      "NIR": 12,
      "Clear": 152
    },
    {
      "time": "20:32:50",
      "F1": 16,
      "F2": 21,
      "F3": 29,
      "F4": 38,
      "F5": 35,
      "F6": 28,
      "F7": 21,
      "F8": 14,
      "NIR": 13,
      "Clear": 158
    },
    {
      "time": "20:32:52",
      "F1": 18,
      "F2": 24,
      "F3": 30,
      "F4": 30,
      "F5": 33,
      "F6": 25,
      "F7": 21,
      "F8": 14,
      "NIR": 12,
      "Clear": 156
    },
    {
      "time": "20:32:54",
      "F1": 19,
      "F2": 20,
      "F3": 24,
      "F4": 35,
      "F5": 30,
      "F6": 23,
      "F7": 22,
      "F8": 13,
      "NIR": 11,
      "Clear": 149
    },
    {
      "time": "20:32:56",
      "F1": 16,
      "F2": 18,
      "F3": 27,
      "F4": 34,
      "F5": 29,
      "F6": 22,
      "F7": 19,
      "F8": 13,
      "NIR": 11,
      "Clear": 142
    },
    {
      "time": "20:32:58",
      "F1": 17,
      "F2": 20,
      "F3": 28,
      "F4": 29,
      "F5": 28,
      "F6": 24,
      "F7": 19,
      "F8": 14,
      "NIR": 11,
      "Clear": 146
    },
    {
      "time": "20:33:00",
      "F1": 17,
      "F2": 24,
      "F3": 27,
      "F4": 31,
      "F5": 30,
      "F6": 26,
      "F7": 22,
      "F8": 13,
      "NIR": 12,
      "Clear": 149
    },
    {
      "time": "20:33:02",
      "F1": 18,
      "F2": 19,
      "F3": 26,
      "F4": 31,
      "F5": 26,
      "F6": 24,
      "F7": 20,
      "F8": 14,
      "NIR": 11,
      "Clear": 139
    },
    {
      "time": "20:33:04",
      "F1": 18,
      "F2": 21,
      "F3": 27,
      "F4": 31,
      "F5": 26,
      "F6": 23,
      "F7": 19,
      "F8": 14,
      "NIR": 10,
      "Clear": 139
    },
    {
      "time": "20:33:06",
      "F1": 16,
      "F2": 17,
      "F3": 21,
      "F4": 28,
      "F5": 28,
      "F6": 22,
      "F7": 20,
      "F8": 14,
      "NIR": 9,
      "Clear": 130
    },
    {
      "time": "20:33:08",
      "F1": 16,
      "F2": 21,
      "F3": 25,
      "F4": 28,
      "F5": 24,
      "F6": 25,
      "F7": 17,
      "F8": 15,
      "NIR": 11,
      "Clear": 136
    },
    {
      "time": "20:33:10",
      "F1": 17,
      "F2": 22,
      "F3": 25,
      "F4": 28,
      "F5": 28,
      "F6": 19,
      "F7": 18,
      "F8": 13,
      "NIR": 10,
      "Clear": 132
    },
    {
      "time": "20:33:12",
      "F1": 15,
      "F2": 20,
      "F3": 25,
      "F4": 25,
      "F5": 24,
      "F6": 19,
      "F7": 19,
      "F8": 13,
      "NIR": 11,
      "Clear": 129
    },
    {
      "time": "20:33:14",
      "F1": 12,
      "F2": 19,
      "F3": 23,
      "F4": 24,
      "F5": 23,
      "F6": 18,
      "F7": 18,
      "F8": 11,
      "NIR": 9,
      "Clear": 119
    },
    {
      "time": "20:33:16",
      "F1": 14,
      "F2": 15,
      "F3": 20,
      "F4": 26,
      "F5": 24,
      "F6": 21,
      "F7": 15,
      "F8": 12,
      "NIR": 8,
      "Clear": 114
    },
    {
      "time": "20:33:18",
      "F1": 12,
      "F2": 17,
      "F3": 20,
      "F4": 28,
      "F5": 20,
      "F6": 19,
      "F7": 16,
      "F8": 12,
      "NIR": 10,
      "Clear": 116
    },
    {
      "time": "20:33:20",
      "F1": 13,
      "F2": 16,
      "F3": 21,
      "F4": 22,
      "F5": 21,
      "F6": 16,
      "F7": 13,
      "F8": 11,
      "NIR": 8,
      "Clear": 108
    },
    {
      "time": "20:33:22",
      "F1": 14,
      "F2": 17,
      "F3": 18,
      "F4": 26,
      "F5": 21,
      "F6": 17,
      "F7": 16,
      "F8": 10,
      "NIR": 9,
      "Clear": 114
    },
    {
      "time": "20:33:24",
      "F1": 11,
      "F2": 16,
      "F3": 17,
      "F4": 20,
      "F5": 22,
      "F6": 15,
      "F7": 15,
      "F8": 9,
      "NIR": 7,
      "Clear": 104
    },
    {
      "time": "20:33:26",
      "F1": 11,
      "F2": 15,
      "F3": 16,
      "F4": 19,
      "F5": 21,
      "F6": 16,
      "F7": 13,
      "F8": 9,
      "NIR": 7,
      "Clear": 102
    },
    {
      "time": "20:33:28",
      "F1": 12,
      "F2": 16,
      "F3": 19,
      "F4": 25,
      "F5": 21,
      "F6": 16,
      "F7": 14,
      "F8": 11,
      "NIR": 7,
      "Clear": 107
    },
    {
      "time": "20:33:30",
      "F1": 13,
      "F2": 15,
      "F3": 18,
      "F4": 25,
      "F5": 18,
      "F6": 17,
      "F7": 14,
      "F8": 10,
      "NIR": 8,
      "Clear": 104
    },
    {
      "time": "20:33:32",
      "F1": 11,
      "F2": 13,
      "F3": 19,
      "F4": 20,
      "F5": 19,
      "F6": 18,
      "F7": 14,
      "F8": 9,
      "NIR": 9,
      "Clear": 103
    },
    {
      "time": "20:33:34",
      "F1": 11,
      "F2": 14,
      "F3": 15,
      "F4": 21,
      "F5": 20,
      "F6": 16,
      "F7": 14,
      "F8": 9,
      "NIR": 7,
      "Clear": 94
    },
    {
      "time": "20:33:36",
      "F1": 10,
      "F2": 12,
      "F3": 16,
      "F4": 19,
      "F5": 16,
      "F6": 15,
      "F7": 13,
      "F8": 8,
      "NIR": 6,
      "Clear": 90
    },
    {
      "time": "20:33:38",
      "F1": 10,
      "F2": 15,
      "F3": 15,
      "F4": 18,
      "F5": 19,
      "F6": 17,
      "F7": 13,
      "F8": 9,
      "NIR": 7,
      "Clear": 94
    },
    {
      "time": "20:33:40",
      "F1": 8,
      "F2": 11,
      "F3": 15,
      "F4": 18,
      "F5": 17,
      "F6": 14,
      "F7": 12,
      "F8": 8,
      "NIR": 6,
      "Clear": 81
    },
    {
      "time": "20:33:42",
      "F1": 9,
      "F2": 12,
      "F3": 13,
      "F4": 16,
      "F5": 17,
      "F6": 13,
      "F7": 12,
      "F8": 8,
      "NIR": 7,
      "Clear": 82
    },
    {
      "time": "20:33:44",
      "F1": 11,
      "F2": 13,
      "F3": 15,
      "F4": 18,
      "F5": 14,
      "F6": 15,
      "F7": 12,
      "F8": 7,
      "NIR": 6,
      "Clear": 83
    },
    {
      "time": "20:33:46",
      "F1": 8,
      "F2": 11,
      "F3": 12,
      "F4": 18,
      "F5": 15,
      "F6": 12,
      "F7": 9,
      "F8": 7,
      "NIR": 5,
      "Clear": 77
    },
    {
      "time": "20:33:48",
      "F1": 8,
      "F2": 11,
      "F3": 12,
      "F4": 15,
      "F5": 15,
      "F6": 13,
      "F7": 10,
      "F8": 6,
      "NIR": 5,
      "Clear": 75
    },
    {
      "time": "20:33:50",
      "F1": 7,
      "F2": 9,
      "F3": 10,
      "F4": 14,
      "F5": 12,
      "F6": 10,
      "F7": 8,
      "F8": 6,
      "NIR": 4,
      "Clear": 62
    },
    {
      "time": "20:33:52",
      "F1": 7,
      "F2": 9,
      "F3": 11,
      "F4": 14,
      "F5": 11,
      "F6": 10,
      "F7": 9,
      "F8": 5,
      "NIR": 4,
      "Clear": 63
    },
    {
      "time": "20:33:54",
      "F1": 6,
      "F2": 7,
      "F3": 9,
      "F4": 10,
      "F5": 11,
      "F6": 8,
      "F7": 7,
      "F8": 5,
      "NIR": 4,
      "Clear": 56
    },
    {
      "time": "20:33:56",
      "F1": 8,
      "F2": 8,
      "F3": 12,
      "F4": 12,
      "F5": 11,
      "F6": 11,
      "F7": 9,
      "F8": 6,
      "NIR": 5,
      "Clear": 63
    },
    {
      "time": "20:33:58",
      "F1": 6,
      "F2": 7,
      "F3": 9,
      "F4": 12,
      "F5": 12,
      "F6": 10,
      "F7": 8,
      "F8": 6,
      "NIR": 4,
      "Clear": 58
    }
  ]
}